topsis/__init__.py
topsis/topsis.py
Topsis_102216131-1.0.1.dist-info/METADATA
Topsis_102216131-1.0.1.dist-info/WHEEL
Topsis_102216131-1.0.1.dist-info/entry_points.txt
Topsis_102216131-1.0.1.dist-info/top_level.txt
Topsis_102216131-1.0.1.dist-info/RECORD
